compare_workdir/__init__.py
compare_workdir/compare_all_workdir_inlists.py
compare_workdir/compare_inlists.py
compare_workdir/merge_column_lists.py
compare_workdir-2.0.dist-info/entry_points.txt
compare_workdir-2.0.dist-info/LICENSE
compare_workdir-2.0.dist-info/WHEEL
compare_workdir-2.0.dist-info/METADATA
compare_workdir-2.0.dist-info/RECORD
