Metadata-Version: 2.1
Name: compare-workdir
Version: 2.0
Summary: Compare MESA inlists and list files without worrying about nesting, comments, and order
Home-page: https://github.com/mathren/compare_workdir_MESA
Author: Mathieu Renzo
Author-email: mrenzo@flatironinstitute.org
Requires-Python: >=3.7,<4.0
Classifier: Programming Language :: Python :: 3
Classifier: Programming Language :: Python :: 3.10
Classifier: Programming Language :: Python :: 3.7
Classifier: Programming Language :: Python :: 3.8
Classifier: Programming Language :: Python :: 3.9
Requires-Dist: click (>=8.0.3,<9.0.0)
Requires-Dist: termcolor (>=1.1.0,<2.0.0)
Project-URL: Repository, https://github.com/mathren/compare_workdir_MESA
